traffic.v
module traffic_light_fsm(
    input clk,
    input rst,
    input ped_btn,
    output reg [2:0] ns_light,  // NS: bit2=RED, bit1=YELLOW, bit0=GREEN
    output reg [2:0] ew_light,  // EW: bit2=RED, bit1=YELLOW, bit0=GREEN
    output reg ped_walk
);

// State encoding
localparam S0 = 3'd0;
localparam S1 = 3'd1;
localparam S2 = 3'd2;
localparam S3 = 3'd3;
localparam S4 = 3'd4;


reg [2:0] state, next_state;
reg [3:0] timer;

// State register
always @(posedge clk or posedge rst) begin
    if (rst) begin
        state <= S0;
        timer <= 0;
    end else begin
        if (ped_btn) begin
            state <= S4;
            timer <= 0;
        end else if (
            (state == S0 && timer == 9)  ||
            (state == S1 && timer == 2)  ||
            (state == S2 && timer == 9)  ||
            (state == S3 && timer == 2)  ||
            (state == S4 && timer == 4)
        ) begin
            state <= next_state;
            timer <= 0;
        end else begin
            timer <= timer + 1;
        end
    end
end

// Next state logic
always @(*) begin
    case(state)
        S0: next_state = S1;
        S1: next_state = S2;
        S2: next_state = S3;
        S3: next_state = S0;
        S4: next_state = S0;
        default: next_state = S0;
    endcase
end

// Output logic
always @(*) begin
    ped_walk = 0;
    case(state)
        S0: begin ns_light = 3'b001; ew_light = 3'b100; end // NS=G, EW=R
        S1: begin ns_light = 3'b010; ew_light = 3'b100; end // NS=Y, EW=R
        S2: begin ns_light = 3'b100; ew_light = 3'b001; end // NS=R, EW=G
        S3: begin ns_light = 3'b100; ew_light = 3'b010; end // NS=R, EW=Y
        S4: begin ns_light = 3'b100; ew_light = 3'b100; ped_walk = 1; end
        default: begin ns_light = 3'b100; ew_light = 3'b100; end
    endcase
end

endmodule

traffic_tb.v
`timescale 1ns/1ps

module traffic_tb;

reg clk, rst, ped_btn;
wire [2:0] ns_light, ew_light;
wire ped_walk;

// Instantiate the FSM
traffic_light_fsm uut (
    .clk(clk),
    .rst(rst),
    .ped_btn(ped_btn),
    .ns_light(ns_light),
    .ew_light(ew_light),
    .ped_walk(ped_walk)
);

// Clock: 10ns period
always #5 clk = ~clk;

initial begin
    // Dump waveforms
    $dumpfile("traffic.vcd");
    $dumpvars(0, traffic_tb);

    // Initialize
    clk = 0; rst = 1; ped_btn = 0;

    // Release reset
    #20 rst = 0;

    // Let it run through S0 and S1
    #150;

    // Press pedestrian button
    ped_btn = 1;
    #10;
    ped_btn = 0;

    // Let pedestrian state complete and cycle continue
    #200;

    $finish;
end

// Monitor outputs
// Monitor outputs
initial begin
    $monitor("Time=%0t | State clk=%b | NS=%b | EW=%b | PED_WALK=%b",
              $time, clk, ns_light, ew_light, ped_walk);
end

// Self-checking assertions
// Self-checking assertions
initial begin
    // Wait for reset to clear
    #25;

    // Check S0: NS=GREEN(001), EW=RED(100)
    if(ns_light === 3'b001 && ew_light === 3'b100)
        $display("PASS: S0 - NS GREEN, EW RED verified");
    else
        $display("FAIL: S0 incorrect - NS=%b EW=%b", ns_light, ew_light);

    // Wait for S1: NS=YELLOW(010), EW=RED(100)
    #95;
    if(ns_light === 3'b010 && ew_light === 3'b100)
        $display("PASS: S1 - NS YELLOW, EW RED verified");
    else
        $display("FAIL: S1 incorrect - NS=%b EW=%b", ns_light, ew_light);

    // Wait for S2: NS=RED(100), EW=GREEN(001)
    #35;
    if(ns_light === 3'b100 && ew_light === 3'b001)
        $display("PASS: S2 - NS RED, EW GREEN verified");
    else
        $display("FAIL: S2 incorrect - NS=%b EW=%b", ns_light, ew_light);

    // Wait for pedestrian state S4
    #40;
    if(ns_light === 3'b100 && ew_light === 3'b100 && ped_walk === 1)
        $display("PASS: S4 - PEDESTRIAN state verified");
    else
        $display("FAIL: S4 incorrect - NS=%b EW=%b PED=%b", ns_light, ew_light, ped_walk);
end
endmodule

traffic.vcd
$date
	Mon Jun 29 17:34:53 2026
$end
$version
	Icarus Verilog
$end
$timescale
	1ps
$end
$scope module traffic_tb $end
$var wire 1 ! ped_walk $end
$var wire 3 " ns_light [2:0] $end
$var wire 3 # ew_light [2:0] $end
$var reg 1 $ clk $end
$var reg 1 % ped_btn $end
$var reg 1 & rst $end
$scope module uut $end
$var wire 1 $ clk $end
$var wire 1 % ped_btn $end
$var wire 1 & rst $end
$var parameter 3 ' S0 $end
$var parameter 3 ( S1 $end
$var parameter 3 ) S2 $end
$var parameter 3 * S3 $end
$var parameter 3 + S4 $end
$var reg 3 , ew_light [2:0] $end
$var reg 3 - next_state [2:0] $end
$var reg 3 . ns_light [2:0] $end
$var reg 1 ! ped_walk $end
$var reg 3 / state [2:0] $end
$var reg 4 0 timer [3:0] $end
$upscope $end
$upscope $end
$enddefinitions $end
$comment Show the parameter values. $end
$dumpall
b100 +
b11 *
b10 )
b1 (
b0 '
$end
#0
$dumpvars
b0 0
b0 /
b1 .
b1 -
b100 ,
1&
0%
0$
b100 #
b1 "
0!
$end
#5000
1$
#10000
0$
#15000
1$
#20000
0$
0&
#25000
b1 0
1$
#30000
0$
#35000
b10 0
1$
#40000
0$
#45000
b11 0
1$
#50000
0$
#55000
b100 0
1$
#60000
0$
#65000
b101 0
1$
#70000
0$
#75000
b110 0
1$
#80000
0$
#85000
b111 0
1$
#90000
0$
#95000
b1000 0
1$
#100000
0$
#105000
b1001 0
1$
#110000
0$
#115000
b10 -
b10 "
b10 .
b0 0
b1 /
1$
#120000
0$
#125000
b1 0
1$
#130000
0$
#135000
b10 0
1$
#140000
0$
#145000
b1 #
b1 ,
b100 "
b100 .
b11 -
b0 0
b10 /
1$
#150000
0$
#155000
b1 0
1$
#160000
0$
#165000
b10 0
1$
#170000
0$
1%
#175000
b0 -
1!
b100 #
b100 ,
b0 0
b100 /
1$
#180000
0$
0%
#185000
b1 0
1$
#190000
0$
#195000
b10 0
1$
#200000
0$
#205000
b11 0
1$
#210000
0$
#215000
b100 0
1$
#220000
0$
#225000
b1 "
b1 .
0!
b1 -
b0 0
b0 /
1$
#230000
0$
#235000
b1 0
1$
#240000
0$
#245000
b10 0
1$
#250000
0$
#255000
b11 0
1$
#260000
0$
#265000
b100 0
1$
#270000
0$
#275000
b101 0
1$
#280000
0$
#285000
b110 0
1$
#290000
0$
#295000
b111 0
1$
#300000
0$
#305000
b1000 0
1$
#310000
0$
#315000
b1001 0
1$
#320000
0$
#325000
b10 -
b10 "
b10 .
b0 0
b1 /
1$
#330000
0$
#335000
b1 0
1$
#340000
0$
#345000
b10 0
1$
#350000
0$
#355000
b1 #
b1 ,
b100 "
b100 .
b11 -
b0 0
b10 /
1$
#360000
0$
#365000
b1 0
1$
#370000
0$
#375000
b10 0
1$
